Metadata-Version: 1.1
Name: django-forums
Version: 0.3.0
Summary: Small standalone django forums application
Home-page: https://github.com/byteweaver/django-forums
Author: byteweaver
Author-email: contact@byteweaver.net
License: MIT License
Platform: OS Independent
Classifier: Environment :: Web Environment
Classifier: Framework :: Django
Classifier: Operating System :: OS Independent
Classifier: Programming Language :: Python
Classifier: Programming Language :: Python :: 3
Classifier: Programming Language :: Python :: 3.4
